counter_dft.v
module counter_dft (
    input wire clk,          // system clock
    input wire reset,        // synchronous reset
    input wire scan_in,      // scan input
    input wire scan_enable,  // enable scan shift
    input wire bist_enable,  // enable BIST mode
    output reg [3:0] q,      // 4-bit counter output
    output wire scan_out     // scan output
);

    reg [3:0] lfsr;          // simple 4-bit LFSR for BIST

    // LFSR for BIST (example: x^4 + x^3 + 1)
    always @(posedge clk) begin
        if (reset)
            lfsr <= 4'b0001;
        else if (bist_enable)
            lfsr <= {lfsr[2:0], lfsr[3] ^ lfsr[2]}; // LFSR shift
    end

    // Main counter with scan and BIST
    always @(posedge clk) begin
        if (reset)
            q <= 4'b0000;
        else if (scan_enable)
            q <= {q[2:0], scan_in};      // scan shift mode
        else if (bist_enable)
            q <= lfsr;                  // BIST mode
        else
            q <= q + 1;                 // normal counting
    end

    assign scan_out = q[0];   // connect LSB to scan chain output

endmodule

counter_dft_tb.v
`timescale 1ns/1ps
module counter_dft_tb;

    reg clk;
    reg reset;
    reg scan_in;
    reg scan_enable;
    reg bist_enable;
    wire [3:0] q;
    wire scan_out;

    // Instantiate DUT
    counter_dft uut (
        .clk(clk),
        .reset(reset),
        .scan_in(scan_in),
        .scan_enable(scan_enable),
        .bist_enable(bist_enable),
        .q(q),
        .scan_out(scan_out)
    );

    // Clock generation (100 MHz)
    always #5 clk = ~clk;

    initial begin
        $dumpfile("counter_dft.vcd");
        $dumpvars(0, counter_dft_tb);

        // Initialize signals
        clk = 0;
        reset = 1;
        scan_in = 0;
        scan_enable = 0;
        bist_enable = 0;

        // Release reset
        #10 reset = 0;

        // Normal counting for 50 ns
        #50;

        // Activate scan mode and shift in a pattern
        scan_enable = 1;
        scan_in = 1;  #10;
        scan_in = 0;  #30;
        scan_enable = 0;

        // Activate BIST mode
        bist_enable = 1;
        #50 bist_enable = 0;

        $finish;
    end

endmodule

counter_dft.vcd
$date
	Sun Sep 28 01:52:36 2025
$end
$version
	Icarus Verilog
$end
$timescale
	1ps
$end
$scope module counter_dft_tb $end
$var wire 1 ! scan_out $end
$var wire 4 " q [3:0] $end
$var reg 1 # bist_enable $end
$var reg 1 $ clk $end
$var reg 1 % reset $end
$var reg 1 & scan_enable $end
$var reg 1 ' scan_in $end
$scope module uut $end
$var wire 1 # bist_enable $end
$var wire 1 $ clk $end
$var wire 1 % reset $end
$var wire 1 & scan_enable $end
$var wire 1 ' scan_in $end
$var wire 1 ! scan_out $end
$var reg 4 ( lfsr [3:0] $end
$var reg 4 ) q [3:0] $end
$upscope $end
$upscope $end
$enddefinitions $end
#0
$dumpvars
bx )
bx (
0'
0&
1%
0$
0#
bx "
x!
$end
#5000
0!
b1 (
b0 "
b0 )
1$
#10000
0$
0%
#15000
1!
b1 "
b1 )
1$
#20000
0$
#25000
0!
b10 "
b10 )
1$
#30000
0$
#35000
1!
b11 "
b11 )
1$
#40000
0$
#45000
0!
b100 "
b100 )
1$
#50000
0$
#55000
1!
b101 "
b101 )
1$
#60000
0$
1'
1&
#65000
b1011 "
b1011 )
1$
#70000
0$
0'
#75000
0!
b110 "
b110 )
1$
#80000
0$
#85000
b1100 "
b1100 )
1$
#90000
0$
#95000
b1000 "
b1000 )
1$
#100000
0$
1#
0&
#105000
1!
b10 (
b1 "
b1 )
1$
#110000
0$
#115000
0!
b10 "
b10 )
b100 (
1$
#120000
0$
#125000
b1001 (
b100 "
b100 )
1$
#130000
0$
#135000
1!
b1001 "
b1001 )
b11 (
1$
#140000
0$
#145000
b110 (
b11 "
b11 )
1$
#150000
0$
0#
