4 bit Counter/counter.v
// counter.v
module counter (
    input wire clk,      // clock
    input wire reset,    // synchronous reset
    output reg [3:0] q   // 4-bit output
);

always @(posedge clk) begin
    if (reset)
        q <= 4'b0000;    // reset to 0
    else
        q <= q + 1;      // increment
end

endmodule

4 bit Counter/counter_tb.v
// counter_tb.v
`timescale 1ns/1ps

module counter_tb;

reg clk;
reg reset;
wire [3:0] q;

// Instantiate the DUT (Device Under Test)
counter uut (
    .clk(clk),
    .reset(reset),
    .q(q)
);

// Clock generation: toggle every 5ns (100 MHz clock)
always #5 clk = ~clk;

initial begin
    // Open VCD file for waveform dumping
    $dumpfile("dump.vcd");
    $dumpvars(0, counter_tb);

    // Initialize
    clk = 0;
    reset = 1;
    #10 reset = 0;    // deassert reset after 10ns

    // Run simulation for 200ns
    #200 $finish;
end

endmodule

4 bit Counter/4 bit Counter.vcd
$date
	Sat Sep 27 16:50:16 2025
$end
$version
	Icarus Verilog
$end
$timescale
	1ps
$end
$scope module counter_tb $end
$var wire 4 ! q [3:0] $end
$var reg 1 " clk $end
$var reg 1 # reset $end
$scope module uut $end
$var wire 1 " clk $end
$var wire 1 # reset $end
$var reg 4 $ q [3:0] $end
$upscope $end
$upscope $end
$enddefinitions $end
#0
$dumpvars
bx $
1#
0"
bx !
$end
#5000
b0 !
b0 $
1"
#10000
0"
0#
#15000
b1 !
b1 $
1"
#20000
0"
#25000
b10 !
b10 $
1"
#30000
0"
#35000
b11 !
b11 $
1"
#40000
0"
#45000
b100 !
b100 $
1"
#50000
0"
#55000
b101 !
b101 $
1"
#60000
0"
#65000
b110 !
b110 $
1"
#70000
0"
#75000
b111 !
b111 $
1"
#80000
0"
#85000
b1000 !
b1000 $
1"
#90000
0"
#95000
b1001 !
b1001 $
1"
#100000
0"
#105000
b1010 !
b1010 $
1"
#110000
0"
#115000
b1011 !
b1011 $
1"
#120000
0"
#125000
b1100 !
b1100 $
1"
#130000
0"
#135000
b1101 !
b1101 $
1"
#140000
0"
#145000
b1110 !
b1110 $
1"
#150000
0"
#155000
b1111 !
b1111 $
1"
#160000
0"
#165000
b0 !
b0 $
1"
#170000
0"
#175000
b1 !
b1 $
1"
#180000
0"
#185000
b10 !
b10 $
1"
#190000
0"
#195000
b11 !
b11 $
1"
#200000
0"
#205000
b100 !
b100 $
1"
