8_bit_shift_register/shift_register.v
module shift_register (

    input wire clk,
    input wire reset, //active high reset
    input wire load, //when high, load all 8 bits parellely
    input wire [7:0] parallel_in, //8 bit data to laod
    input wire shift_en, // shift right on every clock when high
    input wire serial_in,
    output wire [7:0] q,
    output wire serial_out
);

    reg[7:0] reg_sh;
    assign q = reg_sh;
    assign serial_out = reg_sh[0];

 // Sequential behavior: synchronous reset, parallel load priority over shift
    always @(posedge clk) begin
        if (reset) begin
            reg_sh <= {8{1'b0}};
        end else if (load) begin
            reg_sh <= parallel_in;
        end else if (shift_en) begin
            // Right shift: MSB gets serial_in, rest shift towards LSB
            reg_sh <= {serial_in, reg_sh[7:1]};
        end
        // else hold current value
    end

endmodule

8_bit_shift_register/tb_shift_register.v
`timescale 1ns/1ps

module shift_register_tb;

    // Testbench signals
    reg        clk;
    reg        reset;
    reg        load;
    reg        shift_en;
    reg        serial_in;
    reg [7:0]  parallel_in;
    wire [7:0] q;
    wire       serial_out;

    // Instantiate DUT (Device Under Test)
    shift_register DUT (
        .clk(clk),
        .reset(reset),
        .load(load),
        .parallel_in(parallel_in),
        .shift_en(shift_en),
        .serial_in(serial_in),
        .q(q),
        .serial_out(serial_out)
    );

    // Clock generation (10ns period -> 100MHz)
    always #5 clk = ~clk;

    initial begin
        // Dump waveform for GTKWave
        $dumpfile("shift_register.vcd");
        $dumpvars(0, shift_register_tb);

        // Monitor output signals
        $monitor("Time=%0t | q=%b | serial_out=%b", $time, q, serial_out);

        // Initialize signals
        clk = 0;
        reset = 0;
        load = 0;
        shift_en = 0;
        serial_in = 0;
        parallel_in = 8'h00;

        // 1) Apply reset
        #10 reset = 1;
        #10 reset = 0;

        // 2) Parallel load
        parallel_in = 8'b1011_0101;
        load = 1;
        #10 load = 0;

        // 3) Shift right 4 times, feeding in serial_in = 1
        shift_en = 1;
        serial_in = 1;
        #40 shift_en = 0;

        // 4) Finish simulation
        #20;
        $finish;
    end

endmodule

8_bit_shift_register/shift_register.vcd
$date
	Sun Oct 26 01:22:46 2025
$end
$version
	Icarus Verilog
$end
$timescale
	1ps
$end
$scope module shift_register_tb $end
$var wire 1 ! serial_out $end
$var wire 8 " q [7:0] $end
$var reg 1 # clk $end
$var reg 1 $ load $end
$var reg 8 % parallel_in [7:0] $end
$var reg 1 & reset $end
$var reg 1 ' serial_in $end
$var reg 1 ( shift_en $end
$scope module DUT $end
$var wire 1 # clk $end
$var wire 1 $ load $end
$var wire 8 ) parallel_in [7:0] $end
$var wire 8 * q [7:0] $end
$var wire 1 & reset $end
$var wire 1 ' serial_in $end
$var wire 1 ( shift_en $end
$var wire 1 ! serial_out $end
$var reg 8 + reg_sh [7:0] $end
$upscope $end
$upscope $end
$enddefinitions $end
#0
$dumpvars
bx +
bx *
b0 )
0(
0'
0&
b0 %
0$
0#
bx "
x!
$end
#5000
1#
#10000
0#
1&
#15000
0!
b0 "
b0 *
b0 +
1#
#20000
0#
1$
b10110101 %
b10110101 )
0&
#25000
1!
b10110101 "
b10110101 *
b10110101 +
1#
#30000
0#
1'
1(
0$
#35000
0!
b11011010 "
b11011010 *
b11011010 +
1#
#40000
0#
#45000
1!
b11101101 "
b11101101 *
b11101101 +
1#
#50000
0#
#55000
0!
b11110110 "
b11110110 *
b11110110 +
1#
#60000
0#
#65000
1!
b11111011 "
b11111011 *
b11111011 +
1#
#70000
0#
0(
